nsq2arangodb/__init__.py
nsq2arangodb/nsq2arangodb.py
nsq2arangodb-1.0.1.dist-info/LICENSE
nsq2arangodb-1.0.1.dist-info/METADATA
nsq2arangodb-1.0.1.dist-info/WHEEL
nsq2arangodb-1.0.1.dist-info/top_level.txt
nsq2arangodb-1.0.1.dist-info/RECORD
