Metadata-Version: 2.1
Name: nsq2arangodb
Version: 1.0.1
Summary: data transportation from NSQ to ArangoDB
Home-page: https://github.com/larsborn/nsq2arangodb
Author: Lars Wallenborn
License: UNKNOWN
Project-URL: Bug Tracker, https://github.com/larsborn/nsq2arangodb/issues
Platform: UNKNOWN
Classifier: Programming Language :: Python :: 3
Classifier: License :: OSI Approved :: BSD License
Classifier: Operating System :: OS Independent
Requires-Python: >=3.6
License-File: LICENSE
